pulseapi_integration/__init__.py
pulseapi_integration/decorators.py
pulseapi_integration/linalg.py
pulseapi_integration/robot.py
pulseapi_integration/utils.py
pulseapi_integration-0.1.3.dist-info/LICENSE
pulseapi_integration-0.1.3.dist-info/METADATA
pulseapi_integration-0.1.3.dist-info/WHEEL
pulseapi_integration-0.1.3.dist-info/top_level.txt
pulseapi_integration-0.1.3.dist-info/RECORD
